yuna/__init__.py
yuna/lmdb_util.py
yuna/plugins.py
yuna/yuna_repack
yuna_db-0.2.5.dist-info/LICENSE
yuna_db-0.2.5.dist-info/WHEEL
yuna_db-0.2.5.dist-info/METADATA
yuna_db-0.2.5.dist-info/RECORD
