Metadata-Version: 2.1
Name: yuna-db
Version: 0.2.5
Summary: Yuna DB: dict-like semantics for LMDB
Author-email: "Steve R. Hastings" <steve@hastings.org>
Requires-Python: >=3.6
Classifier: License :: OSI Approved :: MIT License
Requires-Dist: lmdb >=1.4.1,<2
